chery_pom_tool/__init__.py
chery_pom_tool/build_tool.py
com_chery/__init__.py
com_chery/chery_pom_root.py
com_chery_pom_root-0.0.3.dist-info/METADATA
com_chery_pom_root-0.0.3.dist-info/WHEEL
com_chery_pom_root-0.0.3.dist-info/top_level.txt
com_chery_pom_root-0.0.3.dist-info/RECORD
